Constituency_tags.py
MFTE.py
MFTE_gui.py
__init__.py
MFTE-1.6.3.dist-info/LICENSE
MFTE-1.6.3.dist-info/METADATA
MFTE-1.6.3.dist-info/WHEEL
MFTE-1.6.3.dist-info/entry_points.txt
MFTE-1.6.3.dist-info/top_level.txt
MFTE-1.6.3.dist-info/RECORD
