Metadata-Version: 2.1
Name: MFTE
Version: 1.6.3
Summary: MFTE (Multi Feature Tagger of English) Python is the Python version based on Le Foll's MFTE written in Perl. It is extended to include semantic tags from Biber (2006) and Biber et al. (1999), including other specific tags.
Home-page: https://github.com/mshakirDr/MFTE
Author: Muhammad Shakir
Author-email: muhammadshakiraziz@outlook.com
Keywords: Grammatical tagging,Multidimensional analysis,MD analysis,Register variation,Multifeature tagging
Classifier: Development Status :: 3 - Alpha
Classifier: Programming Language :: Python :: 3.8
Classifier: Programming Language :: Python :: 3.9
Classifier: Programming Language :: Python :: 3.10
Classifier: License :: OSI Approved :: GNU General Public License v3 (GPLv3)
Classifier: Intended Audience :: Developers
Classifier: Intended Audience :: Other Audience
Classifier: Intended Audience :: Science/Research
Classifier: Intended Audience :: Education
Classifier: Topic :: Text Processing :: Linguistic
Classifier: Operating System :: OS Independent
Requires-Python: >=3.8
License-File: LICENSE
Requires-Dist: pandas >=1.2.4
Requires-Dist: stanza >=1.7.0
Requires-Dist: emoji >=2.9.0
